django_multitenancy/__init__.py
django_multitenancy/constants.py
django_multitenancy/helpers.py
django_multitenancy/mixins.py
django_multitenancy/middleware/__init__.py
django_multitenancy/middleware/base.py
django_multitenancy_plus-0.1.0.dist-info/LICENSE
django_multitenancy_plus-0.1.0.dist-info/METADATA
django_multitenancy_plus-0.1.0.dist-info/WHEEL
django_multitenancy_plus-0.1.0.dist-info/top_level.txt
django_multitenancy_plus-0.1.0.dist-info/RECORD
